README.rst
setup.cfg
setup.py
steam_community_market/__init__.py
steam_community_market/enums.py
steam_community_market/market.py
steam_community_market/request.py
steam_community_market.egg-info/PKG-INFO
steam_community_market.egg-info/SOURCES.txt
steam_community_market.egg-info/dependency_links.txt
steam_community_market.egg-info/requires.txt
steam_community_market.egg-info/top_level.txt