Metadata-Version: 2.1
Name: steam-community-market
Version: 1.2.2
Summary: Get item prices and volumes from the Steam Community Market using Python 3
Home-page: https://github.com/offish/steam_community_market
Author: offish
Author-email: overutilization@gmail.com
License: MIT
Download-URL: https://github.com/offish/steam_community_market/tarball/v1.2.2
Platform: UNKNOWN
Classifier: Programming Language :: Python :: 3
Classifier: License :: OSI Approved :: MIT License
Classifier: Operating System :: OS Independent
Requires-Python: >=3.6
